USB_Quartermaster_common/Communicator.py
USB_Quartermaster_common/Driver.py
USB_Quartermaster_common/Exceptions.py
USB_Quartermaster_common/__init__.py
USB_Quartermaster_common/plugins.py
USB_Quartermaster_common/util.py
usb_quartermaster_common-0.1.0.dist-info/WHEEL
usb_quartermaster_common-0.1.0.dist-info/METADATA
usb_quartermaster_common-0.1.0.dist-info/RECORD
