Metadata-Version: 2.1
Name: usb-quartermaster-common
Version: 0.1.0
Summary: Quartermaster library of common code used between client and server
Author: Tim Laurence
Author-email: timdaman@gmail.com
Requires-Python: >=3.7,<4.0
Classifier: Programming Language :: Python :: 3
Classifier: Programming Language :: Python :: 3.7
Classifier: Programming Language :: Python :: 3.8
